bingX/__init__.py
bingX/api.py
bingX/error.py
bingX/perpetual/__init__.py
bingX/perpetual/v1/Perpetual.py
bingX/perpetual/v1/__init__.py
bingX/perpetual/v1/account.py
bingX/perpetual/v1/market.py
bingX/perpetual/v1/other.py
bingX/perpetual/v1/trade.py
bingX/perpetual/v2/Perpetual.py
bingX/perpetual/v2/__init__.py
bingX/perpetual/v2/account.py
bingX/perpetual/v2/market.py
bingX/perpetual/v2/trade.py
bingX/spot/Spot.py
bingX/spot/__init__.py
bingX/spot/market.py
bingX/spot/other.py
bingX/spot/trade.py
bingX/spot/transfer.py
bingX/standard/Standard.py
bingX/standard/__init__.py
bingX/standard/trade.py
bingX/websocket/__init__.py
bingX/websocket/websocket.py
tests/__init__.py
tests/test_spot.py
tests/test_standard.py
bingX_connector-0.0.7.dist-info/LICENSE
bingX_connector-0.0.7.dist-info/METADATA
bingX_connector-0.0.7.dist-info/WHEEL
bingX_connector-0.0.7.dist-info/top_level.txt
bingX_connector-0.0.7.dist-info/RECORD
