Metadata-Version: 2.1
Name: bingX-connector
Version: 0.0.7
Summary: A simple and easy-to-use interface for developers to access bingX API
Home-page: https://github.com/Ming119/bingX-connector-python
Author: Ming119
License: GPLv3
Platform: UNKNOWN
Classifier: Intended Audience :: Developers
Classifier: Intended Audience :: Financial and Insurance Industry
Classifier: License :: OSI Approved :: GNU General Public License v3 (GPLv3)
Classifier: Programming Language :: Python :: 3
